pyoso/__init__.py
pyoso/analytics.py
pyoso/client.py
pyoso/constants.py
pyoso/engine.py
pyoso/exceptions.py
pyoso/semantic.py
pyoso-0.8.0.dist-info/METADATA
pyoso-0.8.0.dist-info/WHEEL
pyoso-0.8.0.dist-info/RECORD
