Metadata-Version: 2.4
Name: pyoso
Version: 0.8.0
Author-email: Icaro Guerra <icaro@karibalabs.co>
Requires-Python: >=3.8
Requires-Dist: pandas>=1.2.0
Requires-Dist: pydantic>=2.10.5
Requires-Dist: requests>=2.32.4
Requires-Dist: sqlglot>=26.6.0
Provides-Extra: semantic
Requires-Dist: oso-semantic; extra == 'semantic'
